lunavox_tts/Client.py
lunavox_tts/Main.py
lunavox_tts/ModelManager.py
lunavox_tts/PredefinedCharacter.py
lunavox_tts/Server.py
lunavox_tts/__init__.py
lunavox_tts/_internal.py
lunavox_tts/_internal_multi_ref.py
lunavox_tts/Audio/Audio.py
lunavox_tts/Audio/MelExtractor.py
lunavox_tts/Audio/ReferenceAudio.py
lunavox_tts/Audio/SpeakerVector.py
lunavox_tts/Audio/SpectrogramExtractor.py
lunavox_tts/Audio/__init__.py
lunavox_tts/Chinese/ChineseG2P.py
lunavox_tts/Chinese/CorrectPronunciation.py
lunavox_tts/Chinese/Erhua.py
lunavox_tts/Chinese/Resources.py
lunavox_tts/Chinese/ToneSandhi.py
lunavox_tts/Chinese/ZhBert.py
lunavox_tts/Chinese/__init__.py
lunavox_tts/Chinese/chinese2_ported.py
lunavox_tts/Chinese/Normalization/__init__.py
lunavox_tts/Chinese/Normalization/char_convert.py
lunavox_tts/Chinese/Normalization/chronology.py
lunavox_tts/Chinese/Normalization/constants.py
lunavox_tts/Chinese/Normalization/num.py
lunavox_tts/Chinese/Normalization/phonecode.py
lunavox_tts/Chinese/Normalization/quantifier.py
lunavox_tts/Chinese/Normalization/text_normlization.py
lunavox_tts/Converter/__init__.py
lunavox_tts/Converter/load_state_dict.py
lunavox_tts/Converter/utils.py
lunavox_tts/Converter/version_detector.py
lunavox_tts/Converter/v2/Converter.py
lunavox_tts/Converter/v2/EncoderConverter.py
lunavox_tts/Converter/v2/T2SConverter.py
lunavox_tts/Converter/v2/VITSConverter.py
lunavox_tts/Converter/v2/__init__.py
lunavox_tts/Converter/v2ProPlus/PromptEncoderConverter.py
lunavox_tts/Converter/v2ProPlus/__init__.py
lunavox_tts/Core/Inference.py
lunavox_tts/Core/TTSPlayer.py
lunavox_tts/Core/TextFrontend.py
lunavox_tts/Core/__init__.py
lunavox_tts/Data/v2/Keys/t2s_onnx_keys.txt
lunavox_tts/Data/v2/Keys/vits_onnx_keys.txt
lunavox_tts/Data/v2/Models/t2s_encoder_fp32.onnx
lunavox_tts/Data/v2/Models/t2s_first_stage_decoder_fp32.onnx
lunavox_tts/Data/v2/Models/t2s_stage_decoder_fp32.onnx
lunavox_tts/Data/v2/Models/vits_fp32.onnx
lunavox_tts/Data/v2ProPlus/Keys/prompt_encoder_weights.txt
lunavox_tts-1.5.0.dist-info/licenses/LICENSE
lunavox_tts-1.5.0.dist-info/METADATA
lunavox_tts-1.5.0.dist-info/WHEEL
lunavox_tts-1.5.0.dist-info/top_level.txt
lunavox_tts-1.5.0.dist-info/RECORD
