Metadata-Version: 2.4
Name: lunavox-tts
Version: 1.5.0
Summary: GPT-SoVITS ONNX Inference Engine & Model Converter
Author-email: Lux_Luna <525236052@qq.com>
License: MIT
Project-URL: Homepage, https://github.com/Lux-Luna/LunaVox
Classifier: Operating System :: OS Independent
Classifier: Programming Language :: Python :: 3
Classifier: Programming Language :: Python :: 3.9
Classifier: Programming Language :: Python :: 3.10
Classifier: Programming Language :: Python :: 3.11
Classifier: Programming Language :: Python :: 3.12
Classifier: Programming Language :: Python :: 3.13
Requires-Python: >=3.9
License-File: LICENSE
Requires-Dist: onnx
Requires-Dist: onnxruntime==1.22.1
Requires-Dist: numpy<2
Requires-Dist: soundfile
Requires-Dist: soxr
Requires-Dist: pyyaml
Requires-Dist: sounddevice
Requires-Dist: huggingface_hub[hf_xet]
Requires-Dist: fastapi
Requires-Dist: uvicorn[standard]
Requires-Dist: pydantic
Requires-Dist: nltk
Requires-Dist: tokenizers
Provides-Extra: zh
Requires-Dist: pypinyin; extra == "zh"
Requires-Dist: cn2an; extra == "zh"
Requires-Dist: jieba_fast; extra == "zh"
Requires-Dist: g2pM; extra == "zh"
Provides-Extra: ja
Requires-Dist: pyopenjtalk-plus; extra == "ja"
Provides-Extra: dev
Requires-Dist: psutil; extra == "dev"
Requires-Dist: nvidia-ml-py; extra == "dev"
Requires-Dist: build; extra == "dev"
Requires-Dist: twine; extra == "dev"
Provides-Extra: gpu
Requires-Dist: onnxruntime-gpu==1.20.1; extra == "gpu"
Requires-Dist: nvidia-cudnn-cu12; extra == "gpu"
Requires-Dist: nvidia-cublas-cu12; extra == "gpu"
Requires-Dist: nvidia-cuda-runtime-cu12; extra == "gpu"
Dynamic: license-file
